glitch_art_display/jpeg.py
glitch_art_display/main.py
glitch_art_display-1.0.1.dist-info/entry_points.txt
glitch_art_display-1.0.1.dist-info/LICENSE
glitch_art_display-1.0.1.dist-info/WHEEL
glitch_art_display-1.0.1.dist-info/METADATA
glitch_art_display-1.0.1.dist-info/RECORD
