Metadata-Version: 2.1
Name: glitch-art-display
Version: 1.0.1
Summary: Generates .MP4 slideshow with seizure-inducing glitch transitions
License: GPL-3.0
Author: TheTechromancer
Requires-Python: >=3.6,<4.0
Classifier: License :: OSI Approved :: GNU General Public License v3 (GPLv3)
Classifier: Programming Language :: Python :: 3
Classifier: Programming Language :: Python :: 3.6
Classifier: Programming Language :: Python :: 3.7
Classifier: Programming Language :: Python :: 3.8
Classifier: Programming Language :: Python :: 3.9
Requires-Dist: Pillow (>=8.3.1,<9.0.0)
Requires-Dist: click (>=8.0.1,<9.0.0)
